threading_framework/__init__.py
threading_framework/__version__.py
threading_framework/core.py
threading_framework-0.1.3.dist-info/LICENSE
threading_framework-0.1.3.dist-info/METADATA
threading_framework-0.1.3.dist-info/WHEEL
threading_framework-0.1.3.dist-info/top_level.txt
threading_framework-0.1.3.dist-info/RECORD
