Metadata-Version: 2.1
Name: threading_framework
Version: 0.1.3
Summary: A simple framework for threading
Home-page: https://github.com/ccmiogic/threading_framework
Author: CC Miogic
Author-email: ccmiogic@163.com
License: MIT
Classifier: License :: OSI Approved :: MIT License
Classifier: Programming Language :: Python
Classifier: Programming Language :: Python :: 3
Classifier: Programming Language :: Python :: 3.6
Classifier: Programming Language :: Python :: Implementation :: CPython
Classifier: Programming Language :: Python :: Implementation :: PyPy
Requires-Python: >=3.6.0
License-File: LICENSE
